spag/__init__.py
spag/main.py
spag/helpers/__init__.py
spag/helpers/configure.py
spag/helpers/constants.py
spag/helpers/game.py
spag/helpers/urlJoin.py
sp_games-0.0.4.dist-info/METADATA
sp_games-0.0.4.dist-info/WHEEL
sp_games-0.0.4.dist-info/entry_points.txt
sp_games-0.0.4.dist-info/top_level.txt
sp_games-0.0.4.dist-info/RECORD
