Metadata-Version: 2.1
Name: sp-games
Version: 0.0.4
Summary: CLI Utility to extract information from Giant Bomb
Home-page: UNKNOWN
License: UNKNOWN
Platform: UNKNOWN
Classifier: Development Status :: 3 - Alpha
Classifier: Programming Language :: Python :: 3.7
Requires-Dist: argparse
Requires-Dist: PyInquirer
Requires-Dist: requests
Requires-Dist: clint
